{
  "program": "hyperlane.aleo",
  "version": "0.1.0",
  "description": "",
  "license": "MIT",
  "leo": "3.2.0",
  "dependencies": [
    {
      "name": "mailbox.aleo",
      "location": "local",
      "path": "mailbox",
      "edition": null
    },
    {
      "name": "ism_manager.aleo",
      "location": "local",
      "path": "ism_manager",
      "edition": null
    },
    {
      "name": "hook_manager.aleo",
      "location": "local",
      "path": "hook_manager",
      "edition": null
    }
  ],
  "dev_dependencies": null
}
