{
  "program": "hyp_synthetic.aleo",
  "version": "0.1.0",
  "description": "",
  "license": "MIT",
  "leo": "3.2.0",
  "dependencies": [
    {
      "name": "dispatch_proxy.aleo",
      "location": "local",
      "path": "../../dispatch_proxy",
      "edition": null
    },
    {
      "name": "token_registry.aleo",
      "location": "local",
      "path": "../token_registry/token_registry.aleo",
      "edition": null
    },
    {
      "name": "hyp_multisig_core.aleo",
      "location": "local",
      "path": "../../hyp_multisig_core",
      "edition": null
    }
  ],
  "dev_dependencies": null
}
